Workbook

Sheet LEEME
A1: Modelo de ROI - Flujo de crédito preaprobado Expomóvil (SINTÉTICO)
A3: Datos SINTÉTICOS (09-datos, semilla 20261024). Un ROI sintético NO valida una inversión.
A4: Moneda: pesos dominicanos (RD$). Celdas amarillas de la hoja Supuestos = editables.
A5: MODELO ADOPTADO = Opción 3 (ronda 12): versión mínima del portal sobre Camunda, cliente entrega originales en sucursal (sin mensajero) y el tiempo liberado fuera de feria se convierte en caja (no reponer puestos).
A6: Hoja Opciones: compara el modelo original con las opciones 1, 2 y 3 (escenario base). Hojas ROI y FlujoMensual: modelo adoptado.
A7: Caja = menos personal temporal en feria (ROI-4) + tiempo liberado convertido en caja (% editable en Supuestos, fila 24).
A8: ROI año 1 = (beneficio en caja - opex - inversión) / (opex + inversión). Opex = mensajero (si aplica) + mantenimiento.
A9: Beneficio NO incluido: créditos que dejan de perderse por vencimiento (ver ROI, fila 28). Falta el margen por crédito.
A10: Regenerar: node trabajos/mi-proceso/12-roi/conteos.js y luego este script (crear_excel_roi.ps1).

Sheet Opciones
A1: Opciones para subir el ROI (escenario base, año 1) - ronda 12
A3: Concepto | B3: Modelo original | C3: Opción 1: sin mensajero | D3: Opción 2: + tiempo en caja | E3: Opción 3: + versión mínima (ADOPTADA) | F3: Nota
A4: Inversión inicial (RD$) | B4: 3500000 | C4: 3500000 | D4: 3500000 | E4: =Supuestos!D20 -> 1000000 | F4: Portal completo vs versión mínima sobre Camunda
A5: Mantenimiento anual (% de la inversión) | B5: 0.2 | C5: 0.2 | D5: 0.2 | E5: =Supuestos!D21 -> 0.15
A6: ¿Mensajero a domicilio? (1/0) | B6: 1 | C6: 0 | D6: 0 | E6: =Supuestos!D23 -> 0 | F6: Opción 1: el cliente entrega los originales en sucursal o en la feria
A7: % del tiempo liberado que se convierte en caja | B7: 0 | C7: 0 | D7: 1 | E7: =Supuestos!D24 -> 1 | F7: Opción 2: no reponer ~2,7 puestos fuera de feria
A9: Ahorro temporales en feria | B9: =ROI!$D$9 -> 351618.5 | C9: =ROI!$D$9 -> 351618.5 | D9: =ROI!$D$9 -> 351618.5 | E9: =ROI!$D$9 -> 351618.5
A10: Tiempo liberado convertido en caja | B10: =ROI!$D$14*B7 -> 0 | C10: =ROI!$D$14*C7 -> 0 | D10: =ROI!$D$14*D7 -> 1022166.2 | E10: =ROI!$D$14*E7 -> 1022166.2
A11: Beneficio total en caja | B11: =B9+B10 -> 351618.5 | C11: =C9+C10 -> 351618.5 | D11: =D9+D10 -> 1373784.7 | E11: =E9+E10 -> 1373784.7
A12: Mensajero | B12: =SUMPRODUCT((Conteos!$C$4:$C$27="TO-BE")*Conteos!$K$4:$K$27)*Supuestos!$D$19*B6 -> 1020000 | C12: =SUMPRODUCT((Conteos!$C$4:$C$27="TO-BE")*Conteos!$K$4:$K$27)*Supuestos!$D$19*C6 -> 0 | D12: =SUMPRODUCT((Conteos!$C$4:$C$27="TO-BE")*Conteos!$K$4:$K$27)*Supuestos!$D$19*D6 -> 0 | E12: =SUMPRODUCT((Conteos!$C$4:$C$27="TO-BE")*Conteos!$K$4:$K$27)*Supuestos!$D$19*E6 -> 0
A13: Mantenimiento | B13: =B4*B5 -> 700000 | C13: =C4*C5 -> 700000 | D13: =D4*D5 -> 700000 | E13: =E4*E5 -> 150000
A14: Opex | B14: =B12+B13 -> 1720000 | C14: =C12+C13 -> 700000 | D14: =D12+D13 -> 700000 | E14: =E12+E13 -> 150000
A15: Beneficio neto anual (caja) | B15: =B11-B14 -> -1368381.5 | C15: =C11-C14 -> -348381.5 | D15: =D11-D14 -> 673784.74 | E15: =E11-E14 -> 1223784.7
A16: ROI año 1 (caja) | B16: =(B11-B14-B4)/(B14+B4) -> -0.93264013 | C16: =(C11-C14-C4)/(C14+C4) -> -0.91628131 | D16: =(D11-D14-D4)/(D14+D4) -> -0.67290839 | E16: =(E11-E14-E4)/(E14+E4) -> 0.19459543
A17: Meses de recuperación | B17: =IF(B15>0,B4/(B15/12),"No se recupera") -> No se recupera | C17: =IF(C15>0,C4/(C15/12),"No se recupera") -> No se recupera | D17: =IF(D15>0,D4/(D15/12),"No se recupera") -> 62.334448 | E17: =IF(E15>0,E4/(E15/12),"No se recupera") -> 9.805646
A19: La columna de la Opción 3 toma sus valores de la hoja Supuestos (columna Base). Las columnas B a D son editables.

Sheet ROI
A1: ROI del modelo adoptado (Opción 3): tres escenarios de sensibilidad (año 1)
A3: Concepto | B3: Unidad | C3: Conservador | D3: Base | E3: Optimista | F3: Cómo se calcula
A5: Horas de Legal y Despacho AS-IS, meses de feria | B5: h/año | C5: =SUMPRODUCT((Conteos!$C$4:$C$27="AS-IS")*(Conteos!$B$4:$B$27="feria")*(Conteos!$D$4:$D$27*Supuestos!C$11+Conteos!$E$4:$E$27*Supuestos!C$12+Conteos!$F$4:$F$27*Supuestos!C$13+Conteos!$G$4:$G$27*Supuestos!C$14+Conteos!$H$4:$H$27*Supuestos!C$15+Conteos!$I$4:$I$27*Supuestos!C$16+Conteos!$J$4:$J$27*Supuestos!C$17)) -> 1654.75 | D5: =SUMPRODUCT((Conteos!$C$4:$C$27="AS-IS")*(Conteos!$B$4:$B$27="feria")*(Conteos!$D$4:$D$27*Supuestos!D$11+Conteos!$E$4:$E$27*Supuestos!D$12+Conteos!$F$4:$F$27*Supuestos!D$13+Conteos!$G$4:$G$27*Supuestos!D$14+Conteos!$H$4:$H$27*Supuestos!D$15+Conteos!$I$4:$I$27*Supuestos!D$16+Conteos!$J$4:$J$27*Supuestos!D$17)) -> 3309.5 | E5: =SUMPRODUCT((Conteos!$C$4:$C$27="AS-IS")*(Conteos!$B$4:$B$27="feria")*(Conteos!$D$4:$D$27*Supuestos!E$11+Conteos!$E$4:$E$27*Supuestos!E$12+Conteos!$F$4:$F$27*Supuestos!E$13+Conteos!$G$4:$G$27*Supuestos!E$14+Conteos!$H$4:$H$27*Supuestos!E$15+Conteos!$I$4:$I$27*Supuestos!E$16+Conteos!$J$4:$J$27*Supuestos!E$17)) -> 4964.25 | F5: Ejecuciones x horas por ejecución
A6: Horas de Legal y Despacho TO-BE, meses de feria | B6: h/año | C6: =SUMPRODUCT((Conteos!$C$4:$C$27="TO-BE")*(Conteos!$B$4:$B$27="feria")*(Conteos!$D$4:$D$27*Supuestos!C$11+Conteos!$E$4:$E$27*Supuestos!C$12+Conteos!$F$4:$F$27*Supuestos!C$13+Conteos!$G$4:$G$27*Supuestos!C$14+Conteos!$H$4:$H$27*Supuestos!C$15+Conteos!$I$4:$I$27*Supuestos!C$16+Conteos!$J$4:$J$27*Supuestos!C$17)) -> 760.625 | D6: =SUMPRODUCT((Conteos!$C$4:$C$27="TO-BE")*(Conteos!$B$4:$B$27="feria")*(Conteos!$D$4:$D$27*Supuestos!D$11+Conteos!$E$4:$E$27*Supuestos!D$12+Conteos!$F$4:$F$27*Supuestos!D$13+Conteos!$G$4:$G$27*Supuestos!D$14+Conteos!$H$4:$H$27*Supuestos!D$15+Conteos!$I$4:$I$27*Supuestos!D$16+Conteos!$J$4:$J$27*Supuestos!D$17)) -> 1521.25 | E6: =SUMPRODUCT((Conteos!$C$4:$C$27="TO-BE")*(Conteos!$B$4:$B$27="feria")*(Conteos!$D$4:$D$27*Supuestos!E$11+Conteos!$E$4:$E$27*Supuestos!E$12+Conteos!$F$4:$F$27*Supuestos!E$13+Conteos!$G$4:$G$27*Supuestos!E$14+Conteos!$H$4:$H$27*Supuestos!E$15+Conteos!$I$4:$I$27*Supuestos!E$16+Conteos!$J$4:$J$27*Supuestos!E$17)) -> 2281.875 | F6: Ídem
A7: Horas ahorradas en feria | B7: h/año | C7: =C5-C6 -> 894.125 | D7: =D5-D6 -> 1788.25 | E7: =E5-E6 -> 2682.375 | F7: AS-IS - TO-BE
A8: Personal temporal evitado en feria | B8: personas-mes | C8: =C7/(Supuestos!C6*Supuestos!C7) -> 4.6901227 | D8: =D7/(Supuestos!D6*Supuestos!D7) -> 9.3802455 | E8: =E7/(Supuestos!E6*Supuestos!E7) -> 14.070368 | F8: Horas / (días x horas por persona)
A9: AHORRO EN CAJA: menos temporales en feria | B9: RD$/año | C9: =C7*Supuestos!C8 -> 175809.25 | D9: =D7*Supuestos!D8 -> 351618.5 | E9: =E7*Supuestos!E8 -> 527427.75 | F9: Horas ahorradas en feria x costo hora (ROI-4)
A11: Horas AS-IS, meses sin feria | B11: h/año | C11: =SUMPRODUCT((Conteos!$C$4:$C$27="AS-IS")*(Conteos!$B$4:$B$27="no feria")*(Conteos!$D$4:$D$27*Supuestos!C$11+Conteos!$E$4:$E$27*Supuestos!C$12+Conteos!$F$4:$F$27*Supuestos!C$13+Conteos!$G$4:$G$27*Supuestos!C$14+Conteos!$H$4:$H$27*Supuestos!C$15+Conteos!$I$4:$I$27*Supuestos!C$16+Conteos!$J$4:$J$27*Supuestos!C$17)) -> 4903.25 | D11: =SUMPRODUCT((Conteos!$C$4:$C$27="AS-IS")*(Conteos!$B$4:$B$27="no feria")*(Conteos!$D$4:$D$27*Supuestos!D$11+Conteos!$E$4:$E$27*Supuestos!D$12+Conteos!$F$4:$F$27*Supuestos!D$13+Conteos!$G$4:$G$27*Supuestos!D$14+Conteos!$H$4:$H$27*Supuestos!D$15+Conteos!$I$4:$I$27*Supuestos!D$16+Conteos!$J$4:$J$27*Supuestos!D$17)) -> 9806.5 | E11: =SUMPRODUCT((Conteos!$C$4:$C$27="AS-IS")*(Conteos!$B$4:$B$27="no feria")*(Conteos!$D$4:$D$27*Supuestos!E$11+Conteos!$E$4:$E$27*Supuestos!E$12+Conteos!$F$4:$F$27*Supuestos!E$13+Conteos!$G$4:$G$27*Supuestos!E$14+Conteos!$H$4:$H$27*Supuestos!E$15+Conteos!$I$4:$I$27*Supuestos!E$16+Conteos!$J$4:$J$27*Supuestos!E$17)) -> 14709.75
A12: Horas TO-BE, meses sin feria | B12: h/año | C12: =SUMPRODUCT((Conteos!$C$4:$C$27="TO-BE")*(Conteos!$B$4:$B$27="no feria")*(Conteos!$D$4:$D$27*Supuestos!C$11+Conteos!$E$4:$E$27*Supuestos!C$12+Conteos!$F$4:$F$27*Supuestos!C$13+Conteos!$G$4:$G$27*Supuestos!C$14+Conteos!$H$4:$H$27*Supuestos!C$15+Conteos!$I$4:$I$27*Supuestos!C$16+Conteos!$J$4:$J$27*Supuestos!C$17)) -> 2304 | D12: =SUMPRODUCT((Conteos!$C$4:$C$27="TO-BE")*(Conteos!$B$4:$B$27="no feria")*(Conteos!$D$4:$D$27*Supuestos!D$11+Conteos!$E$4:$E$27*Supuestos!D$12+Conteos!$F$4:$F$27*Supuestos!D$13+Conteos!$G$4:$G$27*Supuestos!D$14+Conteos!$H$4:$H$27*Supuestos!D$15+Conteos!$I$4:$I$27*Supuestos!D$16+Conteos!$J$4:$J$27*Supuestos!D$17)) -> 4608 | E12: =SUMPRODUCT((Conteos!$C$4:$C$27="TO-BE")*(Conteos!$B$4:$B$27="no feria")*(Conteos!$D$4:$D$27*Supuestos!E$11+Conteos!$E$4:$E$27*Supuestos!E$12+Conteos!$F$4:$F$27*Supuestos!E$13+Conteos!$G$4:$G$27*Supuestos!E$14+Conteos!$H$4:$H$27*Supuestos!E$15+Conteos!$I$4:$I$27*Supuestos!E$16+Conteos!$J$4:$J$27*Supuestos!E$17)) -> 6912
A13: Horas liberadas fuera de feria | B13: h/año | C13: =C11-C12 -> 2599.25 | D13: =D11-D12 -> 5198.5 | E13: =E11-E12 -> 7797.75 | F13: Capacidad, no caja
A14: Valor del tiempo liberado fuera de feria | B14: RD$/año | C14: =C13*Supuestos!C8 -> 511083.12 | D14: =D13*Supuestos!D8 -> 1022166.2 | E14: =E13*Supuestos!E8 -> 1533249.4 | F14: Horas liberadas x costo hora
A15: AHORRO EN CAJA: tiempo liberado convertido (no reponer puestos) | B15: RD$/año | C15: =C14*Supuestos!C24 -> 255541.56 | D15: =D14*Supuestos!D24 -> 1022166.2 | E15: =E14*Supuestos!E24 -> 1533249.4 | F15: Opción 2: valor x % convertido
A16: Recogidas a domicilio | B16: recogidas/año | C16: =SUMPRODUCT((Conteos!$C$4:$C$27="TO-BE")*Conteos!$K$4:$K$27)*Supuestos!C23 -> 0 | D16: =SUMPRODUCT((Conteos!$C$4:$C$27="TO-BE")*Conteos!$K$4:$K$27)*Supuestos!D23 -> 0 | E16: =SUMPRODUCT((Conteos!$C$4:$C$27="TO-BE")*Conteos!$K$4:$K$27)*Supuestos!E23 -> 0 | F16: TB_ACT_RECOGER; 0 si el cliente entrega en sucursal (Opción 1)
A17: Costo del mensajero certificado | B17: RD$/año | C17: =C16*Supuestos!C19 -> 0 | D17: =D16*Supuestos!D19 -> 0 | E17: =E16*Supuestos!E19 -> 0 | F17: Recogidas x costo por recogida
A18: Mantenimiento del portal | B18: RD$/año | C18: =Supuestos!C22 -> 300000 | D18: =Supuestos!D22 -> 150000 | E18: =Supuestos!E22 -> 70000
A19: Opex año 1 | B19: RD$/año | C19: =C17+C18 -> 300000 | D19: =D17+D18 -> 150000 | E19: =E17+E18 -> 70000 | F19: Mensajero + mantenimiento
A20: Inversión inicial (versión mínima) | B20: RD$ | C20: =Supuestos!C20 -> 1500000 | D20: =Supuestos!D20 -> 1000000 | E20: =Supuestos!E20 -> 700000 | F20: Opción 3
A21: Beneficio total en caja | B21: RD$/año | C21: =C9+C15 -> 431350.81 | D21: =D9+D15 -> 1373784.7 | E21: =E9+E15 -> 2060677.1 | F21: Temporales en feria + tiempo convertido
A22: Beneficio neto operativo anual (caja) | B22: RD$/año | C22: =C21-C19 -> 131350.81 | D22: =D21-D19 -> 1223784.7 | E22: =E21-E19 -> 1990677.1 | F22: Beneficio en caja - opex
A23: ROI año 1 (caja) | B23: % | C23: =(C21-C19-C20)/(C19+C20) -> -0.76036066 | D23: =(D21-D19-D20)/(D19+D20) -> 0.19459543 | E23: =(E21-E19-E20)/(E19+E20) -> 1.676204 | F23: (beneficio - opex - inversión) / (opex + inversión)
A24: Meses de recuperación | B24: meses | C24: =IF(C22>0,C20/(C22/12),"No se recupera") -> 137.0376 | D24: =IF(D22>0,D20/(D22/12),"No se recupera") -> 9.805646 | E24: =IF(E22>0,E20/(E22/12),"No se recupera") -> 4.2196697 | F24: Inversión / beneficio neto mensual
A26: ROI año 1 sin convertir el tiempo liberado en caja (referencia) | B26: % | C26: =(C9-C19-C20)/(C19+C20) -> -0.90232819 | D26: =(D9-D19-D20)/(D19+D20) -> -0.69424478 | E26: =(E9-E19-E20)/(E19+E20) -> -0.31502889 | F26: Si no se ejecuta la Opción 2
A28: NO INCLUIDO: créditos que dejan de perderse por vencimiento | B28: créditos/año | C28: =SUMPRODUCT((Conteos!$C$4:$C$27="AS-IS")*Conteos!$M$4:$M$27)-SUMPRODUCT((Conteos!$C$4:$C$27="TO-BE")*Conteos!$M$4:$M$27) -> 153 | D28: =SUMPRODUCT((Conteos!$C$4:$C$27="AS-IS")*Conteos!$M$4:$M$27)-SUMPRODUCT((Conteos!$C$4:$C$27="TO-BE")*Conteos!$M$4:$M$27) -> 153 | E28: =SUMPRODUCT((Conteos!$C$4:$C$27="AS-IS")*Conteos!$M$4:$M$27)-SUMPRODUCT((Conteos!$C$4:$C$27="TO-BE")*Conteos!$M$4:$M$27) -> 153 | F28: Falta el margen por crédito para monetizarlo

Sheet Supuestos
A1: Supuestos (editar celdas amarillas)
A3: Variable | B3: Unidad | C3: Conservador | D3: Base | E3: Optimista | F3: Estado / fuente
A4: Salario mínimo mensual (empresa grande) | B4: RD$/mes | C4: 29988 | D4: 29988 | E4: 29988 | F4: Declarado (ROI-1). Res. CNS-01-2025, vigente desde 01-02-2026
A5: Factor de costo del empleador | B5: x | C5: 1.25 | D5: 1.25 | E5: 1.25 | F5: SUPUESTO S-1: TSS empleador ~16 % + regalía pascual 8,3 %
A6: Días laborables por mes | B6: días | C6: 23.83 | D6: 23.83 | E6: 23.83 | F6: Práctica laboral RD
A7: Horas por día | B7: h | C7: 8 | D7: 8 | E7: 8 | F7: Declarado (ROI-2)
A8: Costo por hora | B8: RD$/h | C8: =C4*C5/(C6*C7) -> 196.62715 | D8: =D4*D5/(D6*D7) -> 196.62715 | E8: =E4*E5/(E6*E7) -> 196.62715 | F8: Fórmula
A10: Horas de trabajo por ejecución de cada actividad
A11: ACT_006 Recopilar expediente (Legal) | B11: h/ejecución | C11: 0.75 | D11: 1.5 | E11: 2.25 | F11: HIPÓTESIS H-R1: horas de trabajo real por expediente
A12: ACT_007 Escanear documentación (Legal) | B12: h/ejecución | C12: 0.5 | D12: 1 | E12: 1.5 | F12: HIPÓTESIS H-R1
A13: ACT_008 Verificar expediente en papel (Despacho) | B13: h/ejecución | C13: 0.5 | D13: 1 | E13: 1.5 | F13: HIPÓTESIS H-R1
A14: TB_ACT_VERIF Verificar expediente digital (Despacho) | B14: h/ejecución | C14: 0.25 | D14: 0.5 | E14: 0.75 | F14: HIPÓTESIS H-R1
A15: TB_ACT_PEDIR Pedir documento corregido (Despacho) | B15: h/ejecución | C15: 0.125 | D15: 0.25 | E15: 0.375 | F15: HIPÓTESIS H-R1
A16: TB_ACT_RECOP_ORIG Recopilar originales (Legal) | B16: h/ejecución | C16: 0.5 | D16: 1 | E16: 1.5 | F16: HIPÓTESIS H-R1
A17: TB_ACT_ESCANEAR Escanear originales (Legal) | B17: h/ejecución | C17: 0.5 | D17: 1 | E17: 1.5 | F17: HIPÓTESIS H-R1
A19: Costo por recogida del mensajero certificado | B19: RD$/recogida | C19: 500 | D19: 400 | E19: 300 | F19: SUPUESTO S-2 (solo si hay mensajero, fila 23)
A20: Inversión inicial: versión mínima del portal sobre Camunda | B20: RD$ | C20: 1500000 | D20: 1000000 | E20: 700000 | F20: SUPUESTO S-3b (Opción 3, ronda 12)
A21: Mantenimiento anual (% de la inversión) | B21: % | C21: 0.2 | D21: 0.15 | E21: 0.1 | F21: SUPUESTO S-4b (Opción 3)
A22: Mantenimiento anual | B22: RD$/año | C22: =C20*C21 -> 300000 | D22: =D20*D21 -> 150000 | E22: =E20*E21 -> 70000 | F22: Fórmula
A23: ¿Mensajero a domicilio? (1 = sí, 0 = cliente entrega en sucursal) | B23: 36526 | C23: 0 | D23: 0 | E23: 0 | F23: Decisión Opción 1 (ronda 12)
A24: % del tiempo liberado fuera de feria que se convierte en caja | B24: % | C24: 0.5 | D24: 1 | E24: 1 | F24: Decisión Opción 2 (ronda 12): no reponer puestos; SUPUESTO S-5 en conservador

Sheet Conteos
A1: Ejecuciones de actividades por mes y escenario (desde 09-datos, SINTÉTICO)
A3: mes | B3: temporada | C3: escenario | D3: ACT_006 | E3: ACT_007 | F3: ACT_008 | G3: TB_ACT_VERIF | H3: TB_ACT_PEDIR | I3: TB_ACT_RECOP_ORIG | J3: TB_ACT_ESCANEAR | K3: TB_ACT_RECOGER | L3: entraron_expediente | M3: cerradas_vencimiento | N3: sobres_enviados
A4: 2026-01 | B4: no feria | C4: AS-IS | D4: 286 | E4: 264 | F4: 264 | G4: 0 | H4: 0 | I4: 0 | J4: 0 | K4: 0 | L4: 236 | M4: 22 | N4: 214
A5: 2026-01 | B5: no feria | C5: TO-BE | D5: 50 | E5: 43 | F5: 43 | G5: 183 | H5: 6 | I5: 8 | J5: 177 | K5: 177 | L5: 236 | M5: 22 | N5: 214
A6: 2026-02 | B6: feria | C6: AS-IS | D6: 470 | E6: 439 | F6: 439 | G6: 0 | H6: 0 | I6: 0 | J6: 0 | K6: 0 | L6: 378 | M6: 31 | N6: 347
A7: 2026-02 | B7: feria | C7: TO-BE | D7: 82 | E7: 80 | F7: 80 | G7: 308 | H7: 13 | I7: 11 | J7: 295 | K7: 295 | L7: 378 | M7: 15 | N7: 363
A8: 2026-03 | B8: no feria | C8: AS-IS | D8: 286 | E8: 263 | F8: 263 | G8: 0 | H8: 0 | I8: 0 | J8: 0 | K8: 0 | L8: 232 | M8: 23 | N8: 209
A9: 2026-03 | B9: no feria | C9: TO-BE | D9: 37 | E9: 33 | F9: 33 | G9: 202 | H9: 12 | I9: 12 | J9: 190 | K9: 190 | L9: 232 | M9: 15 | N9: 217
A10: 2026-04 | B10: no feria | C10: AS-IS | D10: 294 | E10: 265 | F10: 265 | G10: 0 | H10: 0 | I10: 0 | J10: 0 | K10: 0 | L10: 246 | M10: 29 | N10: 217
A11: 2026-04 | B11: no feria | C11: TO-BE | D11: 57 | E11: 53 | F11: 53 | G11: 203 | H11: 10 | I11: 9 | J11: 193 | K11: 193 | L11: 246 | M11: 12 | N11: 234
A12: 2026-05 | B12: no feria | C12: AS-IS | D12: 310 | E12: 277 | F12: 277 | G12: 0 | H12: 0 | I12: 0 | J12: 0 | K12: 0 | L12: 247 | M12: 33 | N12: 214
A13: 2026-05 | B13: no feria | C13: TO-BE | D13: 45 | E13: 43 | F13: 43 | G13: 212 | H13: 8 | I13: 7 | J13: 204 | K13: 204 | L13: 247 | M13: 10 | N13: 237
A14: 2026-06 | B14: no feria | C14: AS-IS | D14: 248 | E14: 219 | F14: 219 | G14: 0 | H14: 0 | I14: 0 | J14: 0 | K14: 0 | L14: 220 | M14: 29 | N14: 191
A15: 2026-06 | B15: no feria | C15: TO-BE | D15: 45 | E15: 38 | F15: 38 | G15: 183 | H15: 9 | I15: 9 | J15: 174 | K15: 174 | L15: 220 | M15: 18 | N15: 202
... A27: 2026-12 | B27: no feria | C27: TO-BE | D27: 45 | E27: 43 | F27: 43 | G27: 202 | H27: 8 | I27: 10 | J27: 194 | K27: 194 | L27: 230 | M27: 4 | N27: 226

Sheet FlujoMensual
A1: Flujo mensual - modelo adoptado (Opción 3), escenario BASE (RD$)
A3: mes | B3: temporada | C3: Horas AS-IS | D3: Horas TO-BE | E3: Horas ahorradas | F3: Ahorro temporales (feria) | G3: Tiempo convertido en caja | H3: Mensajero | I3: Mantenimiento | J3: Neto en caja | K3: Acumulado
A4: Mes 0 | B4: inversión | J4: =-Supuestos!D20 -> -1000000 | K4: =J4 -> -1000000
A5: =Conteos!A4 -> 2026-01 | B5: =Conteos!B4 -> no feria | C5: =Conteos!D4*Supuestos!$D$11+Conteos!E4*Supuestos!$D$12+Conteos!F4*Supuestos!$D$13+Conteos!G4*Supuestos!$D$14+Conteos!H4*Supuestos!$D$15+Conteos!I4*Supuestos!$D$16+Conteos!J4*Supuestos!$D$17 -> 957 | D5: =Conteos!D5*Supuestos!$D$11+Conteos!E5*Supuestos!$D$12+Conteos!F5*Supuestos!$D$13+Conteos!G5*Supuestos!$D$14+Conteos!H5*Supuestos!$D$15+Conteos!I5*Supuestos!$D$16+Conteos!J5*Supuestos!$D$17 -> 439 | E5: =C5-D5 -> 518 | F5: =IF(B5="feria",E5*Supuestos!$D$8,0) -> 0 | G5: =IF(B5="no feria",E5*Supuestos!$D$8*Supuestos!$D$24,0) -> 101852.86 | H5: =Conteos!K5*Supuestos!$D$19*Supuestos!$D$23 -> 0 | I5: =Supuestos!$D$22/12 -> 12500 | J5: =F5+G5-H5-I5 -> 89352.864 | K5: =K4+J5 -> -910647.14
A6: =Conteos!A6 -> 2026-02 | B6: =Conteos!B6 -> feria | C6: =Conteos!D6*Supuestos!$D$11+Conteos!E6*Supuestos!$D$12+Conteos!F6*Supuestos!$D$13+Conteos!G6*Supuestos!$D$14+Conteos!H6*Supuestos!$D$15+Conteos!I6*Supuestos!$D$16+Conteos!J6*Supuestos!$D$17 -> 1583 | D6: =Conteos!D7*Supuestos!$D$11+Conteos!E7*Supuestos!$D$12+Conteos!F7*Supuestos!$D$13+Conteos!G7*Supuestos!$D$14+Conteos!H7*Supuestos!$D$15+Conteos!I7*Supuestos!$D$16+Conteos!J7*Supuestos!$D$17 -> 746.25 | E6: =C6-D6 -> 836.75 | F6: =IF(B6="feria",E6*Supuestos!$D$8,0) -> 164527.77 | G6: =IF(B6="no feria",E6*Supuestos!$D$8*Supuestos!$D$24,0) -> 0 | H6: =Conteos!K7*Supuestos!$D$19*Supuestos!$D$23 -> 0 | I6: =Supuestos!$D$22/12 -> 12500 | J6: =F6+G6-H6-I6 -> 152027.77 | K6: =K5+J6 -> -758619.37
A7: =Conteos!A8 -> 2026-03 | B7: =Conteos!B8 -> no feria | C7: =Conteos!D8*Supuestos!$D$11+Conteos!E8*Supuestos!$D$12+Conteos!F8*Supuestos!$D$13+Conteos!G8*Supuestos!$D$14+Conteos!H8*Supuestos!$D$15+Conteos!I8*Supuestos!$D$16+Conteos!J8*Supuestos!$D$17 -> 955 | D7: =Conteos!D9*Supuestos!$D$11+Conteos!E9*Supuestos!$D$12+Conteos!F9*Supuestos!$D$13+Conteos!G9*Supuestos!$D$14+Conteos!H9*Supuestos!$D$15+Conteos!I9*Supuestos!$D$16+Conteos!J9*Supuestos!$D$17 -> 427.5 | E7: =C7-D7 -> 527.5 | F7: =IF(B7="feria",E7*Supuestos!$D$8,0) -> 0 | G7: =IF(B7="no feria",E7*Supuestos!$D$8*Supuestos!$D$24,0) -> 103720.82 | H7: =Conteos!K9*Supuestos!$D$19*Supuestos!$D$23 -> 0 | I7: =Supuestos!$D$22/12 -> 12500 | J7: =F7+G7-H7-I7 -> 91220.822 | K7: =K6+J7 -> -667398.55
A8: =Conteos!A10 -> 2026-04 | B8: =Conteos!B10 -> no feria | C8: =Conteos!D10*Supuestos!$D$11+Conteos!E10*Supuestos!$D$12+Conteos!F10*Supuestos!$D$13+Conteos!G10*Supuestos!$D$14+Conteos!H10*Supuestos!$D$15+Conteos!I10*Supuestos!$D$16+Conteos!J10*Supuestos!$D$17 -> 971 | D8: =Conteos!D11*Supuestos!$D$11+Conteos!E11*Supuestos!$D$12+Conteos!F11*Supuestos!$D$13+Conteos!G11*Supuestos!$D$14+Conteos!H11*Supuestos!$D$15+Conteos!I11*Supuestos!$D$16+Conteos!J11*Supuestos!$D$17 -> 497.5 | E8: =C8-D8 -> 473.5 | F8: =IF(B8="feria",E8*Supuestos!$D$8,0) -> 0 | G8: =IF(B8="no feria",E8*Supuestos!$D$8*Supuestos!$D$24,0) -> 93102.956 | H8: =Conteos!K11*Supuestos!$D$19*Supuestos!$D$23 -> 0 | I8: =Supuestos!$D$22/12 -> 12500 | J8: =F8+G8-H8-I8 -> 80602.956 | K8: =K7+J8 -> -586795.59
A9: =Conteos!A12 -> 2026-05 | B9: =Conteos!B12 -> no feria | C9: =Conteos!D12*Supuestos!$D$11+Conteos!E12*Supuestos!$D$12+Conteos!F12*Supuestos!$D$13+Conteos!G12*Supuestos!$D$14+Conteos!H12*Supuestos!$D$15+Conteos!I12*Supuestos!$D$16+Conteos!J12*Supuestos!$D$17 -> 1019 | D9: =Conteos!D13*Supuestos!$D$11+Conteos!E13*Supuestos!$D$12+Conteos!F13*Supuestos!$D$13+Conteos!G13*Supuestos!$D$14+Conteos!H13*Supuestos!$D$15+Conteos!I13*Supuestos!$D$16+Conteos!J13*Supuestos!$D$17 -> 472.5 | E9: =C9-D9 -> 546.5 | F9: =IF(B9="feria",E9*Supuestos!$D$8,0) -> 0 | G9: =IF(B9="no feria",E9*Supuestos!$D$8*Supuestos!$D$24,0) -> 107456.74 | H9: =Conteos!K13*Supuestos!$D$19*Supuestos!$D$23 -> 0 | I9: =Supuestos!$D$22/12 -> 12500 | J9: =F9+G9-H9-I9 -> 94956.738 | K9: =K8+J9 -> -491838.85
A10: =Conteos!A14 -> 2026-06 | B10: =Conteos!B14 -> no feria | C10: =Conteos!D14*Supuestos!$D$11+Conteos!E14*Supuestos!$D$12+Conteos!F14*Supuestos!$D$13+Conteos!G14*Supuestos!$D$14+Conteos!H14*Supuestos!$D$15+Conteos!I14*Supuestos!$D$16+Conteos!J14*Supuestos!$D$17 -> 810 | D10: =Conteos!D15*Supuestos!$D$11+Conteos!E15*Supuestos!$D$12+Conteos!F15*Supuestos!$D$13+Conteos!G15*Supuestos!$D$14+Conteos!H15*Supuestos!$D$15+Conteos!I15*Supuestos!$D$16+Conteos!J15*Supuestos!$D$17 -> 420.25 | E10: =C10-D10 -> 389.75 | F10: =IF(B10="feria",E10*Supuestos!$D$8,0) -> 0 | G10: =IF(B10="no feria",E10*Supuestos!$D$8*Supuestos!$D$24,0) -> 76635.432 | H10: =Conteos!K15*Supuestos!$D$19*Supuestos!$D$23 -> 0 | I10: =Supuestos!$D$22/12 -> 12500 | J10: =F10+G10-H10-I10 -> 64135.432 | K10: =K9+J10 -> -427703.42
A11: =Conteos!A16 -> 2026-07 | B11: =Conteos!B16 -> no feria | C11: =Conteos!D16*Supuestos!$D$11+Conteos!E16*Supuestos!$D$12+Conteos!F16*Supuestos!$D$13+Conteos!G16*Supuestos!$D$14+Conteos!H16*Supuestos!$D$15+Conteos!I16*Supuestos!$D$16+Conteos!J16*Supuestos!$D$17 -> 1068.5 | D11: =Conteos!D17*Supuestos!$D$11+Conteos!E17*Supuestos!$D$12+Conteos!F17*Supuestos!$D$13+Conteos!G17*Supuestos!$D$14+Conteos!H17*Supuestos!$D$15+Conteos!I17*Supuestos!$D$16+Conteos!J17*Supuestos!$D$17 -> 532.75 | E11: =C11-D11 -> 535.75 | F11: =IF(B11="feria",E11*Supuestos!$D$8,0) -> 0 | G11: =IF(B11="no feria",E11*Supuestos!$D$8*Supuestos!$D$24,0) -> 105343 | H11: =Conteos!K17*Supuestos!$D$19*Supuestos!$D$23 -> 0 | I11: =Supuestos!$D$22/12 -> 12500 | J11: =F11+G11-H11-I11 -> 92842.996 | K11: =K10+J11 -> -334860.42
A12: =Conteos!A18 -> 2026-08 | B12: =Conteos!B18 -> no feria | C12: =Conteos!D18*Supuestos!$D$11+Conteos!E18*Supuestos!$D$12+Conteos!F18*Supuestos!$D$13+Conteos!G18*Supuestos!$D$14+Conteos!H18*Supuestos!$D$15+Conteos!I18*Supuestos!$D$16+Conteos!J18*Supuestos!$D$17 -> 1018 | D12: =Conteos!D19*Supuestos!$D$11+Conteos!E19*Supuestos!$D$12+Conteos!F19*Supuestos!$D$13+Conteos!G19*Supuestos!$D$14+Conteos!H19*Supuestos!$D$15+Conteos!I19*Supuestos!$D$16+Conteos!J19*Supuestos!$D$17 -> 461.75 | E12: =C12-D12 -> 556.25 | F12: =IF(B12="feria",E12*Supuestos!$D$8,0) -> 0 | G12: =IF(B12="no feria",E12*Supuestos!$D$8*Supuestos!$D$24,0) -> 109373.85 | H12: =Conteos!K19*Supuestos!$D$19*Supuestos!$D$23 -> 0 | I12: =Supuestos!$D$22/12 -> 12500 | J12: =F12+G12-H12-I12 -> 96873.853 | K12: =K11+J12 -> -237986.57
A13: =Conteos!A20 -> 2026-09 | B13: =Conteos!B20 -> no feria | C13: =Conteos!D20*Supuestos!$D$11+Conteos!E20*Supuestos!$D$12+Conteos!F20*Supuestos!$D$13+Conteos!G20*Supuestos!$D$14+Conteos!H20*Supuestos!$D$15+Conteos!I20*Supuestos!$D$16+Conteos!J20*Supuestos!$D$17 -> 1069.5 | D13: =Conteos!D21*Supuestos!$D$11+Conteos!E21*Supuestos!$D$12+Conteos!F21*Supuestos!$D$13+Conteos!G21*Supuestos!$D$14+Conteos!H21*Supuestos!$D$15+Conteos!I21*Supuestos!$D$16+Conteos!J21*Supuestos!$D$17 -> 465 | E13: =C13-D13 -> 604.5 | F13: =IF(B13="feria",E13*Supuestos!$D$8,0) -> 0 | G13: =IF(B13="no feria",E13*Supuestos!$D$8*Supuestos!$D$24,0) -> 118861.11 | H13: =Conteos!K21*Supuestos!$D$19*Supuestos!$D$23 -> 0 | I13: =Supuestos!$D$22/12 -> 12500 | J13: =F13+G13-H13-I13 -> 106361.11 | K13: =K12+J13 -> -131625.46
A14: =Conteos!A22 -> 2026-10 | B14: =Conteos!B22 -> no feria | C14: =Conteos!D22*Supuestos!$D$11+Conteos!E22*Supuestos!$D$12+Conteos!F22*Supuestos!$D$13+Conteos!G22*Supuestos!$D$14+Conteos!H22*Supuestos!$D$15+Conteos!I22*Supuestos!$D$16+Conteos!J22*Supuestos!$D$17 -> 1020 | D14: =Conteos!D23*Supuestos!$D$11+Conteos!E23*Supuestos!$D$12+Conteos!F23*Supuestos!$D$13+Conteos!G23*Supuestos!$D$14+Conteos!H23*Supuestos!$D$15+Conteos!I23*Supuestos!$D$16+Conteos!J23*Supuestos!$D$17 -> 431.25 | E14: =C14-D14 -> 588.75 | F14: =IF(B14="feria",E14*Supuestos!$D$8,0) -> 0 | G14: =IF(B14="no feria",E14*Supuestos!$D$8*Supuestos!$D$24,0) -> 115764.23 | H14: =Conteos!K23*Supuestos!$D$19*Supuestos!$D$23 -> 0 | I14: =Supuestos!$D$22/12 -> 12500 | J14: =F14+G14-H14-I14 -> 103264.23 | K14: =K13+J14 -> -28361.224
A15: =Conteos!A24 -> 2026-11 | B15: =Conteos!B24 -> feria | C15: =Conteos!D24*Supuestos!$D$11+Conteos!E24*Supuestos!$D$12+Conteos!F24*Supuestos!$D$13+Conteos!G24*Supuestos!$D$14+Conteos!H24*Supuestos!$D$15+Conteos!I24*Supuestos!$D$16+Conteos!J24*Supuestos!$D$17 -> 1726.5 | D15: =Conteos!D25*Supuestos!$D$11+Conteos!E25*Supuestos!$D$12+Conteos!F25*Supuestos!$D$13+Conteos!G25*Supuestos!$D$14+Conteos!H25*Supuestos!$D$15+Conteos!I25*Supuestos!$D$16+Conteos!J25*Supuestos!$D$17 -> 775 | E15: =C15-D15 -> 951.5 | F15: =IF(B15="feria",E15*Supuestos!$D$8,0) -> 187090.73 | G15: =IF(B15="no feria",E15*Supuestos!$D$8*Supuestos!$D$24,0) -> 0 | H15: =Conteos!K25*Supuestos!$D$19*Supuestos!$D$23 -> 0 | I15: =Supuestos!$D$22/12 -> 12500 | J15: =F15+G15-H15-I15 -> 174590.73 | K15: =K14+J15 -> 146229.51
A16: =Conteos!A26 -> 2026-12 | B16: =Conteos!B26 -> no feria | C16: =Conteos!D26*Supuestos!$D$11+Conteos!E26*Supuestos!$D$12+Conteos!F26*Supuestos!$D$13+Conteos!G26*Supuestos!$D$14+Conteos!H26*Supuestos!$D$15+Conteos!I26*Supuestos!$D$16+Conteos!J26*Supuestos!$D$17 -> 918.5 | D16: =Conteos!D27*Supuestos!$D$11+Conteos!E27*Supuestos!$D$12+Conteos!F27*Supuestos!$D$13+Conteos!G27*Supuestos!$D$14+Conteos!H27*Supuestos!$D$15+Conteos!I27*Supuestos!$D$16+Conteos!J27*Supuestos!$D$17 -> 460.5 | E16: =C16-D16 -> 458 | F16: =IF(B16="feria",E16*Supuestos!$D$8,0) -> 0 | G16: =IF(B16="no feria",E16*Supuestos!$D$8*Supuestos!$D$24,0) -> 90055.235 | H16: =Conteos!K27*Supuestos!$D$19*Supuestos!$D$23 -> 0 | I16: =Supuestos!$D$22/12 -> 12500 | J16: =F16+G16-H16-I16 -> 77555.235 | K16: =K15+J16 -> 223784.74
